README.md
setup.py
wttech_aem/__init__.py
wttech_aem/_utilities.py
wttech_aem/provider.py
wttech_aem/pulumi-plugin.json
wttech_aem/py.typed
wttech_aem.egg-info/PKG-INFO
wttech_aem.egg-info/SOURCES.txt
wttech_aem.egg-info/dependency_links.txt
wttech_aem.egg-info/not-zip-safe
wttech_aem.egg-info/requires.txt
wttech_aem.egg-info/top_level.txt
wttech_aem/compose/__init__.py
wttech_aem/compose/_inputs.py
wttech_aem/compose/instance.py
wttech_aem/compose/outputs.py