Metadata-Version: 2.1
Name: wttech_aem
Version: 0.9.1
Requires-Python: >=3.8
Requires-Dist: parver>=0.2.1
Requires-Dist: pulumi<4.0.0,>=3.56.0
Requires-Dist: semver>=2.8.1
